openfhe_numpy/__init__.py
openfhe_numpy/build-config.txt
openfhe_numpy/openfhe_numpy.cpython-312-x86_64-linux-gnu.so
openfhe_numpy/operations/__init__.py
openfhe_numpy/operations/crypto_helper.py
openfhe_numpy/operations/dispatch.py
openfhe_numpy/operations/matrix_api.py
openfhe_numpy/operations/matrix_arithmetic.py
openfhe_numpy/tensor/__init__.py
openfhe_numpy/tensor/block_ctarray.py
openfhe_numpy/tensor/block_tensor.py
openfhe_numpy/tensor/constructors.py
openfhe_numpy/tensor/ctarray.py
openfhe_numpy/tensor/ptarray.py
openfhe_numpy/tensor/tensor.py
openfhe_numpy/utils/__init__.py
openfhe_numpy/utils/constants.py
openfhe_numpy/utils/errors.py
openfhe_numpy/utils/format.py
openfhe_numpy/utils/matlib.py
openfhe_numpy/utils/packing.py
openfhe_numpy/utils/typecheck.py
openfhe_numpy-1.4.2.0.0.24.4.dist-info/METADATA
openfhe_numpy-1.4.2.0.0.24.4.dist-info/WHEEL
openfhe_numpy-1.4.2.0.0.24.4.dist-info/top_level.txt
openfhe_numpy-1.4.2.0.0.24.4.dist-info/RECORD
openfhe_numpy-1.4.2.0.0.24.4.dist-info/licenses/LICENSE
