Metadata-Version: 2.4
Name: openfhe_numpy
Version: 1.4.2.0.0.24.4
Summary: Numpy Matrix extention for OpenFHE C++ library.
Home-page: https://github.com/openfheorg/openfhe-numpy
Author: OpenFHE Team
Author-email: contact@openfhe.org
License: BSD-2-Clause
Classifier: Operating System :: POSIX :: Linux
Requires-Python: >=3.12
License-File: LICENSE
Requires-Dist: openfhe<1.4.3,>=1.4.2
Requires-Dist: numpy>=1.24
Dynamic: author
Dynamic: author-email
Dynamic: classifier
Dynamic: description
Dynamic: description-content-type
Dynamic: home-page
Dynamic: license
Dynamic: license-file
Dynamic: requires-dist
Dynamic: requires-python
Dynamic: summary
